llmtokens/__init__.py
llmtokens/cli.py
llmtokens-0.1.1.dist-info/METADATA
llmtokens-0.1.1.dist-info/WHEEL
llmtokens-0.1.1.dist-info/entry_points.txt
llmtokens-0.1.1.dist-info/licenses/LICENSE
llmtokens-0.1.1.dist-info/RECORD
