Metadata-Version: 2.4
Name: llmtokens
Version: 0.1.1
Summary: Count tokens and explore chat templates using HuggingFace tokenizers or OpenAI tiktoken
Project-URL: Homepage, https://github.com/slukyano/llmtokens
Project-URL: Repository, https://github.com/slukyano/llmtokens
Project-URL: Issues, https://github.com/slukyano/llmtokens/issues
Author-email: Stanislav Lukyanov <stanlukyanov@gmail.com>
License: MIT
License-File: LICENSE
Classifier: Development Status :: 3 - Alpha
Classifier: Environment :: Console
Classifier: Intended Audience :: Developers
Classifier: License :: OSI Approved :: MIT License
Classifier: Programming Language :: Python :: 3
Classifier: Topic :: Scientific/Engineering :: Artificial Intelligence
Classifier: Topic :: Text Processing
Requires-Python: >=3.12
Requires-Dist: huggingface-hub
Requires-Dist: jinja2
Requires-Dist: tiktoken
Requires-Dist: tokenizers
Provides-Extra: dev
Requires-Dist: pytest; extra == 'dev'
